{
	"id" : "collection-inspector",
	"name" : "Collection inspector",
	"type" : "collection-analysis",
	"phase" : "collection-exploration",
	"description" : "With this recipe it is possible to: 1) select collections, 2) inspect their metadata, 3) perform data analytics tasks on their metadata (e.g., detect incomplete data, observe value distributions along date fields), and 4) send them to the other browsing and search recipes.",
	"recipeDescription" : "<p>With this recipe it is possible to:</p><br /> 1) select collections, <br />2) inspect their metadata, <br />3) perform data analytics tasks on their metadata (e.g., detect incomplete data, observe value distributions along date fields), and <br /> 4) send them to the other browsing and search recipes.",
	"inRecipeList" : true,
	"ingredients" : {
		"collectionAnalyser" : {
			"collectionSelector" : false,
			"fieldAnalysisStats" : false,
			"collectionStats" : false,
			"timeline" : false
		},
		"recipes" : [
			{
				"id" : "comparative-search",
				"label" : "Comparative Search",
				"path": "recipe/comparative-search"
			},
			{
				"id" : "single-search",
				"label" : "Single Search",
				"path": "recipe/single-search"
			}
		]
	}
}