{
	"id" : "single-search",
	"name" : "Multi-layered single collection search",
	"type" : "single-search",
	"phase" : "search",
	"description" : "Dedicated recipe for searching/exploring through a single collection and all available annotation layers for that collection (e.g., automatically-generated, user-generated, archival generated).",
	"inRecipeList" : true,
	"ingredients" : {
		"collectionSelector" : true,
		"aggregationView" : "box",
		"dateRangeSelector" : "date-picker",
		"itemDetailsPath" : "recipe/default-item-details"
	}
}